pdal_parallelizer/__init__.py
pdal_parallelizer/bounds.py
pdal_parallelizer/cloud.py
pdal_parallelizer/do.py
pdal_parallelizer/file_manager.py
pdal_parallelizer/pipeline_wrapper.py
pdal_parallelizer/tile.py
pdal_parallelizer/pdal_parallelizer_cli/__init__.py
pdal_parallelizer/pdal_parallelizer_cli/__main__.py
pdal_parallelizer-2.1.0.dist-info/LICENSE.txt
pdal_parallelizer-2.1.0.dist-info/METADATA
pdal_parallelizer-2.1.0.dist-info/WHEEL
pdal_parallelizer-2.1.0.dist-info/entry_points.txt
pdal_parallelizer-2.1.0.dist-info/top_level.txt
pdal_parallelizer-2.1.0.dist-info/RECORD
