Metadata-Version: 2.1
Name: pdal-parallelizer
Version: 2.1.0
Summary: A simple tool for use pdal with parallel execution
License: BSD 3-Clause License
Keywords: pdal,parallelizer,dask
Classifier: Programming Language :: Python :: 3
License-File: LICENSE.txt
Requires-Dist: click (<=8.1.3)
Requires-Dist: pdal (<=3.2.2)
Requires-Dist: dask (<=2023.1.1)
Requires-Dist: distributed (<=2023.1.1)
Requires-Dist: twine (<=4.0.2)
Requires-Dist: pandas (<=1.5.3)
Requires-Dist: pyproj (<=3.4.1)
Requires-Dist: numpy (<=1.24.2)
